Workbook

Sheet Presupuesto
A1: Presupuesto Mensual
A3: Rubros | B3: Ingresos | C3: Gastos
A4: Salario | B4: 12000
A5: Variables | B5: 4000
A6: Eventuales | B6: 6000
A7: Servicio público agua | C7: 400
A8: Servicio público luz | C8: 200
A9: Servicio público gas | C9: 100
A10: Mantenimiento casa | C10: 650
A11: Diversión | C11: 350
A12: Educación | C12: 2000
A13: Combustible | C13: 300
A14: Créditos | C14: 1500
A15: Ropa y accesorios | C15: 5000
A16: Mascota | C16: 600
A17: Varios | C17: 3000
A18: Total | B18: =SUM(B4:B17) -> 22000 | C18: =SUM(C7:C17) -> 14100
A19: Margen | C19: =B18-C18 -> 7900
A20: % de holgura | C20: 0.1
A21: Margen Neto | C21: =C19-C19*C20 -> 7110

Sheet Clientes
A1: Funciones Condicionales
A3: Cliente | B3: Tipo Clte | C3: Antigüedad (años) | D3: Horas trabajadas | E3: Valor Hora | F3: Descuento | G3: Honor Totales
A4: Coca Cola | B4: Alimentos | C4: 1 | D4: 34 | E4: $1,500 | F4: $0 | G4: 51000
A5: Mc Donald's | B5: Gastronomia | C5: 2 | D5: 23 | E5: $1,500 | F5: $0 | G5: 34500
A6: Pritty | B6: Alimentos | C6: 3 | D6: 65 | E6: $1,500 | F6: $9,750 | G6: 87750
A7: Volkswagen | B7: Autos | C7: 4 | D7: 23 | E7: $1,500 | F7: $3,450 | G7: 31050
A8: Mostaza | B8: Gastronomia | C8: 2 | D8: 22 | E8: $1,800 | F8: $0 | G8: 39600
A9: Grido | B9: Alimentos | C9: 2 | D9: 33 | E9: $2,000 | F9: $0 | G9: 66000
A12: Count if | B12: Gastronomia | C12: =COUNTIF(B4:B9, B12) -> 2
A15: SUMIF | B15: Alimentos | C15: =SUMIF(B4:B9,B15,G4:G9) -> 204750

Sheet Comparar Valores
A3: Lista A | B3: Lista B | C3: Operadores | D3: Funcion SI
A4: 10 | B4: 12 | C4: =A4=B4 -> FALSE | D4: =IF(A4=B4, "Verdadero", "Falso") -> Falso
A5: 20 | B5: 6 | C5: =A5>B5 -> TRUE | D5: =IF(A5>=B5, "Verdadero", "Falso") -> Verdadero
A6: 30 | B6: 12 | C6: =B6>A6 -> FALSE | D6: =IF(A6<=B6, "Verdadero", "Falso") -> Falso
A7: 40 | B7: 16 | C7: =A7<>B7 -> TRUE | D7: =IF(A7<>B7, "Verdadero", "Falso") -> Verdadero

Sheet Buscar-lOOKUP
B3: Código | C3: Nombre | D3: Edad | E3: Salario | G3: Buscar | H3: Resultado
B4: Cod001 | C4: Juan Perez | D4: 25 | E4: $800.00 | G4: Cod001 | H4: =LOOKUP(G4,B4:B13,C4:C13) -> Juan Perez
B5: Cod002 | C5: Andres Sanchez | D5: 45 | E5: $1,500.00 | G5: Cod002 | H5: =LOOKUP(G5,B5:B14,C5:C14) -> Andres Sanchez
B6: Cod003 | C6: Mario Gonzalez | D6: 34 | E6: $1,200.00 | G6: Cod003 | H6: =LOOKUP(G6,B6:B15,C6:C15) -> Mario Gonzalez
B7: Cod004 | C7: María Dominguez | D7: 34 | E7: $1,200.00 | G7: Cod004 | H7: =LOOKUP(G7,B7:B16,C7:C16) -> María Dominguez
B8: Cod005 | C8: Juana Velez | D8: 23 | E8: $760.00 | G8: Cod005 | H8: =LOOKUP(G8,B8:B17,C8:C17) -> Juana Velez
B9: Cod006 | C9: Pedro Urdiales | D9: 54 | E9: $1,650.00 | G9: Cod006 | H9: =LOOKUP(G9,B9:B18,C9:C18) -> Pedro Urdiales
B10: Cod007 | C10: Samanta Loja | D10: 47 | E10: $1,400.00 | G10: Cod007 | H10: =LOOKUP(G10,B10:B19,C10:C19) -> Samanta Loja
B11: Cod008 | C11: Melina Lima | D11: 42 | E11: $1,350.00 | G11: Cod008 | H11: =LOOKUP(G11,B11:B20,C11:C20) -> Melina Lima
B12: Cod009 | C12: Melisa Ruales | D12: 37 | E12: $1,150.00 | G12: Cod009 | H12: =LOOKUP(G12,B12:B21,C12:C21) -> Melisa Ruales
B13: Cod010 | C13: Esteban Arredondo | D13: 35 | E13: $1,100.00 | G13: Cod010 | H13: =LOOKUP(G13,B13:B22,C13:C22) -> Esteban Arredondo
G14: Cod011 | H14: =LOOKUP(G14,B14:B23,C14:C23) -> #N/A

Sheet BuscaRV-VLOOKUP
B4: Código | C4: Nombre | D4: Edad | E4: Salario | G4: Buscar | H4: Resultado
B5: Cod001 | C5: Juan Perez | D5: 25 | E5: $800.00 | G5: Cod002 | H5: =VLOOKUP(G5,B5:E14,3,0) -> 45
B6: Cod002 | C6: Andres Sanchez | D6: 45 | E6: $1,500.00 | G6: Cod002 | H6: =VLOOKUP(G6,B6:E15,3,0) -> 45
B7: Cod003 | C7: Mario Gonzalez | D7: 34 | E7: $1,200.00 | G7: Cod003 | H7: =VLOOKUP(G7,B7:E16,3,0) -> 34
B8: Cod004 | C8: María Dominguez | D8: 34 | E8: $1,200.00 | G8: Cod004 | H8: =VLOOKUP(G8,B8:E17,3,0) -> 34
B9: Cod005 | C9: Juana Velez | D9: 23 | E9: $760.00 | G9: Cod005 | H9: =VLOOKUP(G9,B9:E18,3,0) -> 23
B10: Cod006 | C10: Pedro Urdiales | D10: 54 | E10: $1,650.00 | G10: Cod006 | H10: =VLOOKUP(G10,B10:E19,3,0) -> 54
B11: Cod007 | C11: Samanta Loja | D11: 47 | E11: $1,400.00 | G11: Cod007 | H11: =VLOOKUP(G11,B11:E20,3,0) -> 47
B12: Cod008 | C12: Melina Lima | D12: 42 | E12: $1,350.00 | G12: Cod008 | H12: =VLOOKUP(G12,B12:E21,3,0) -> 42
B13: Cod009 | C13: Melisa Ruales | D13: 37 | E13: $1,150.00 | G13: Cod009 | H13: =VLOOKUP(G13,B13:E22,3,0) -> 37
B14: Cod010 | C14: Esteban Arredondo | D14: 35 | E14: $1,100.00 | G14: Cod010 | H14: =VLOOKUP(G14,B14:E23,3,0) -> 35
G15: Cod011 | H15: =VLOOKUP(G15,B15:E24,3,0) -> #N/A

Sheet BuscarH-Hlookup
B4: Código | C4: Cod001 | D4: Cod002 | E4: Cod003 | F4: Cod004 | G4: Cod005 | H4: Cod006 | I4: Cod007 | J4: Cod008 | K4: Cod009 | L4: Cod010
B5: Nombre | C5: Juan Perez | D5: Andres Sanchez | E5: Mario Gonzalez | F5: María Dominguez | G5: Juana Velez | H5: Pedro Urdiales | I5: Samanta Loja | J5: Melina Lima | K5: Melisa Ruales | L5: Esteban Arredondo
B6: Edad | C6: 25 | D6: 45 | E6: 34 | F6: 34 | G6: 23 | H6: 54 | I6: 47 | J6: 42 | K6: 37 | L6: 35
B7: Salario | C7: $800.00 | D7: $1,500.00 | E7: $1,200.00 | F7: $1,200.00 | G7: $760.00 | H7: $1,650.00 | I7: $1,400.00 | J7: $1,350.00 | K7: $1,150.00 | L7: $1,100.00
B9: Buscar | C9: Cod001 | D9: Cod002
B10: Resultado | C10: =HLOOKUP(C9,C4:L7,2) -> Juan Perez | D10: =HLOOKUP(D9,C4:L7,4) -> $1,500.00

Sheet BuscarX-Xlookup
B4: Código | C4: Nombre | D4: Edad | E4: Salario | G4: Buscar | H4: Resultado
B5: Cod001 | C5: Juan Perez | D5: 25 | E5: $800.00 | G5: Cod011 | H5: =_xlfn.XLOOKUP(G5,B5:B14,D5:D14, "No encontrado") -> No encontrado
B6: Cod002 | C6: Andres Sanchez | D6: 45 | E6: $1,500.00 | G6: Cod001 | H6: =_xlfn.XLOOKUP(G6,B5:B14,C5:C14, " No encontrado") -> Juan Perez
B7: Cod003 | C7: Mario Gonzalez | D7: 34 | E7: $1,200.00 | G7: Cod002 | H7: =_xlfn.XLOOKUP(G7,B6:B15,C6:C15, " No encontrado") -> Andres Sanchez
B8: Cod004 | C8: María Dominguez | D8: 34 | E8: $1,200.00 | G8: Cod003 | H8: =_xlfn.XLOOKUP(G8,B7:B16,C7:C16, " No encontrado") -> Mario Gonzalez
B9: Cod005 | C9: Juana Velez | D9: 23 | E9: $760.00 | G9: Cod004 | H9: =_xlfn.XLOOKUP(G9,B8:B17,C8:C17, " No encontrado") -> María Dominguez
B10: Cod006 | C10: Pedro Urdiales | D10: 54 | E10: $1,650.00 | G10: Cod005 | H10: =_xlfn.XLOOKUP(G10,B9:B18,C9:C18, " No encontrado") -> Juana Velez
B11: Cod007 | C11: Samanta Loja | D11: 47 | E11: $1,400.00 | G11: Cod006 | H11: =_xlfn.XLOOKUP(G11,B10:B19,C10:C19, " No encontrado") -> Pedro Urdiales
B12: Cod008 | C12: Melina Lima | D12: 42 | E12: $1,350.00 | G12: Cod007 | H12: =_xlfn.XLOOKUP(G12,B11:B20,C11:C20, " No encontrado") -> Samanta Loja
B13: Cod009 | C13: Melisa Ruales | D13: 37 | E13: $1,150.00 | G13: Cod008 | H13: =_xlfn.XLOOKUP(G13,B12:B21,C12:C21, " No encontrado") -> Melina Lima
B14: Cod010 | C14: Esteban Arredondo | D14: 35 | E14: $1,100.00 | G14: Cod009 | H14: =_xlfn.XLOOKUP(G14,B13:B22,C13:C22, " No encontrado") -> Melisa Ruales

Sheet INTERMEDIO
C4: Tabla de IVA
C5: Otros Productos | D5: 0.08
C6: Importado Especiales | D6: 0.18
C7: Productos tipo A hasta tipo F | D7: 0.19

Sheet Datos
A1: Planilla mes de eptiembre de 2021
A3: Producto | B3: Cantidad | C3: Valor Uni. | D3: Subtotal | E3: Valor del Descto. | F3: Total
A4: Producto A | B4: 10 | C4: 10 | D4: 100 | E4: =D4*'Referencia a otras hojas'!$B$5 -> 3
A5: Producto B | B5: 20 | C5: 25 | D5: 500 | E5: =D5*'Referencia a otras hojas'!$B$5 -> 15
A6: Producto C | B6: 5 | C6: 13 | D6: 65 | E6: =D6*'Referencia a otras hojas'!$B$5 -> 1.95
A7: Producto D | B7: 12 | C7: 500 | D7: 6 | E7: =D7*'Referencia a otras hojas'!$B$5 -> 0.18
A8: Producto E | B8: 50 | C8: 2.8 | D8: 140 | E8: =D8*'Referencia a otras hojas'!$B$5 -> 4.2
A9: Producto F | B9: 10 | C9: 1 | D9: 10 | E9: =D9*'Referencia a otras hojas'!$B$5 -> 0.3
A11: Valor | B11: 10 | C11: 25 | D11: 13 | E11: 500 | F11: 2800 | G11: 1000
A12: Valor IVA: | B12: =B11*INTERMEDIO!$D$7 -> 1.9 | C12: =C11*INTERMEDIO!$D$7 -> 4.75 | D12: =D11*INTERMEDIO!$D$7 -> 2.47 | E12: =E11*INTERMEDIO!$D$7 -> 95 | F12: =F11*INTERMEDIO!$D$7 -> 532 | G12: =G11*INTERMEDIO!$D$7 -> 190

Sheet Referencia a otras hojas
A1: Descuentos autorizados por mes
A3: Mes | B3: % Descuento
A4: Agosto | B4: 0.02
A5: Septiembre | B5: 0.03
A6: Octubre | B6: 0.05
A7: Noviembre | B7: 0.045
A8: Diciembre | B8: 0.01

Sheet Formatos y Estilos  de celdas
D4: Cantidad | E4: Gastos
C5: Producto | D5: 90 | E5: 1056870 | H5: Cantidad | I5: Gastos
C6: Producto | D6: 71 | E6: 1397706 | G6: Producto | H6: 90 | I6: 1056870
C7: Producto | D7: 61 | E7: 835212 | G7: Producto | H7: 71 | I7: 1397706
C8: Producto | D8: 99 | E8: 1730124 | G8: Producto | H8: 61 | I8: 835212
G9: Producto | H9: 99 | I9: 1730124
D11: Cantidad | E11: Gastos
C12: Producto | D12: 90 | E12: 1056870
C13: Producto | D13: 71 | E13: 1397706
C14: Producto | D14: 61 | E14: 835212
C15: Producto | D15: 99 | E15: 1730124

Sheet Formato Condicional
C5: Cantidad | D5: Gastos | H5: Cantidad
B6: Producto | C6: 90 | D6: 1056870 | G6: Producto | H6: 59
B7: Producto | C7: 71 | D7: 1397706 | G7: Producto | H7: 54
B8: Producto | C8: 61 | D8: 835212 | G8: Producto | H8: 75
B9: Producto | C9: 99 | D9: 1730124 | G9: Producto | H9: 57
G10: Producto | H10: 63
G11: Producto | H11: 86
G12: Producto | H12: 100
G13: Producto | H13: 57
G14: Producto | H14: 54
G15: Producto | H15: 88
