Workbook

Sheet Productos
A1: Sistema-Facturacion-2026
A3: ID | B3: Producto | C3: Precio | D3: Categoria
A4: P001 | B4: Laptop | C4: 4500 | D4: Tecnologia
A5: P002 | B5: Mouse | C5: 800 | D5: Tecnologia
A6: P003 | B6: Teclado | C6: 1500 | D6: Tecnologia
A7: P004 | B7: Silla | C7: 3500 | D7: Muebles
A8: P005 | B8: Escritorio | C8: 8000 | D8: Muebles
A9: P006 | B9: Monitor | C9: 12000 | D9: Tecnologia
A10: P007 | B10: Impresora | C10: 8500 | D10: Tecnologia
A11: P008 | B11: Auriculares | C11: 2500 | D11: Accesorios

Sheet Clientes
A1: ID | B1: Nombre | C1: Telefono | D1: Ciudad
A2: C001 | B2: Juan perez | C2: 809-555-0101 | D2: Santo Domingo
A3: C002 | B3: Maria Lopez | C3: 809-555-0102 | D3: Santiago
A4: C003 | B4: Carlos Ruiz | C4: 809-555-0103 | D4: La vega
A5: C004 | B5: Ana Garcia | C5: 809-555-0104 | D5: San Pedro
A6: C005 | B6: Pedro Santos | C6: 809-555-0105 | D6: Bonao

Sheet Factura
A1: FACTURA
A2: No.Factura: | B2: 001
A3: Fecha: | B3: 46190
A4: ID Cliente: | B4: C005
A5: Nombre: | B5: =_xlfn.XLOOKUP(B4,Clientes!A:A,Clientes!B:B,"Cliente no encontrado") -> Pedro Santos
A6: Ciudad: | B6: =_xlfn.XLOOKUP(B4,Clientes!A:A,Clientes!D:D,"Ciudad no encontrada") -> Bonao
N9: ID Producto | O9: Descripcion | P9: Cantidad | Q9: Precio Unit. | R9: Total
A10: ID Producto | B10: Descripcion | C10: Cantidad | D10: Precio Unit. | E10: Total | N10: P001 | O10: =_xlfn.XLOOKUP(N10,Productos!N:N,Productos!O:O,"Producto no encontrado") -> Producto no encontrado | P10: 2 | Q10: =_xlfn.XLOOKUP(N10,Productos!N:N,Productos!P:P,0) -> 0 | R10: =P10*Q10 -> 0
A11: P001 | B11: =_xlfn.XLOOKUP(A11,Productos!A:A,Productos!B:B,"Producto no encontrado") -> Laptop | C11: 2 | D11: =_xlfn.XLOOKUP(A11,Productos!A:A,Productos!C:C,0) -> 4500 | E11: =C11*D11 -> 9000 | N11: P002 | O11: =_xlfn.XLOOKUP(N11,Productos!N:N,Productos!O:O,"Producto no encontrado") -> Producto no encontrado | P11: 1 | Q11: =_xlfn.XLOOKUP(N11,Productos!N:N,Productos!P:P,0) -> 0 | R11: =P11*Q11 -> 0
A12: P002 | B12: =_xlfn.XLOOKUP(A12,Productos!A:A,Productos!B:B,"Producto no encontrado") -> Mouse | C12: 1 | D12: =_xlfn.XLOOKUP(A12,Productos!A:A,Productos!C:C,0) -> 800 | E12: =C12*D12 -> 800 | N12: P003 | O12: =_xlfn.XLOOKUP(N12,Productos!N:N,Productos!O:O,"Producto no encontrado") -> Producto no encontrado | P12: 3 | Q12: =_xlfn.XLOOKUP(N12,Productos!N:N,Productos!P:P,0) -> 0 | R12: =P12*Q12 -> 0
A13: P003 | B13: =_xlfn.XLOOKUP(A13,Productos!A:A,Productos!B:B,"Producto no encontrado") -> Teclado | C13: 3 | D13: =_xlfn.XLOOKUP(A13,Productos!A:A,Productos!C:C,0) -> 1500 | E13: =C13*D13 -> 4500 | N13: P004 | O13: =_xlfn.XLOOKUP(N13,Productos!N:N,Productos!O:O,"Producto no encontrado") -> Producto no encontrado | P13: 1 | Q13: =_xlfn.XLOOKUP(N13,Productos!N:N,Productos!P:P,0) -> 0 | R13: =P13*Q13 -> 0
A14: P004 | B14: =_xlfn.XLOOKUP(A14,Productos!A:A,Productos!B:B,"Producto no encontrado") -> Silla | C14: 1 | D14: =_xlfn.XLOOKUP(A14,Productos!A:A,Productos!C:C,0) -> 3500 | E14: =C14*D14 -> 3500 | N14: P005 | O14: =_xlfn.XLOOKUP(N14,Productos!N:N,Productos!O:O,"Producto no encontrado") -> Producto no encontrado | P14: 2 | Q14: =_xlfn.XLOOKUP(N14,Productos!N:N,Productos!P:P,0) -> 0 | R14: =P14*Q14 -> 0
A15: P005 | B15: =_xlfn.XLOOKUP(A15,Productos!A:A,Productos!B:B,"Producto no encontrado") -> Escritorio | C15: 2 | D15: =_xlfn.XLOOKUP(A15,Productos!A:A,Productos!C:C,0) -> 8000 | E15: =C15*D15 -> 16000
Q16: Total | R16: =SUM(R10:R14) -> 0
D17: Total | E17: =SUM(E11:E15) -> 33800
B20: =_xlfn.XLOOKUP(A2,Clientes!A:A,Clientes!B:B,"Cliente no encontrado") -> Cliente no encontrado

Sheet Empleados
A1: Sistema-Nomina-2026
A4: ID | B4: Nombre | C4: Cargo | D4: Departamento | E4: Salario Base
A5: E001 | B5: Juan Perez | C5: Analista | D5: Ventas | E5: 45000
A6: E002 | B6: Maria Lopez | C6: Tecnico | D6: TI | E6: 55000
A7: E003 | B7: Carlos Ruiz | C7: Coordinador | D7: RRHH | E7: 65000
A8: E004 | B8: Ana Garcia | C8: Analista | D8: Contabilidad | E8: 50000
A9: E005 | B9: Pedro Santos | C9: Supervisor | D9: Operaciones | E9: 70000

Sheet Deducciones
A1: Deduccion | B1: Porcentaje | C1: Descricpion
A2: AFP | B2: 0.0287 | C2: Fondo de pensiones
A3: SFS | B3: 0.0304 | C3: Seguro salud
A4: ISR | B4: 0.1 | C4: Impuesto sobre la renta
A5: AFP Empleador | B5: 0.071 | C5: Aporte empleador pensiones
A6: SFS Empleador | B6: 0.0709 | C6: Aporteempleador salud

Sheet Nomina
A2: ID | B2: Nombre | C2: Cargo | D2: Salario Base | E2: AFP | F2: SFS | G2: ISR | H2: Salario Neto
A3: E001 | B3: {=_xlfn.XLOOKUP(A3,Empleados!A:A,Empleados!B:B, Empleados no encontrado)} -> Juan Perez | C3: =_xlfn.XLOOKUP(A3,Empleados!A:A,Empleados!C:C,"Cargo No encontrado") -> Analista | D3: =_xlfn.XLOOKUP(A3,Empleados!A:A,Empleados!E:E, "No encontrado") -> 45000 | E3: =D3*_xlfn.XLOOKUP("AFP",Deducciones!A:A,Deducciones!B:B,0) -> 1291.5 | F3: =D3*_xlfn.XLOOKUP("SFS",Deducciones!A:A,Deducciones!B:B,0) -> 1368 | G3: =D3*_xlfn.XLOOKUP("ISR",Deducciones!A:A,Deducciones!B:B,0) -> 4500 | H3: =D3-E3-F3-G3 -> 37840.5
A4: E002 | B4: {=_xlfn.XLOOKUP(A4,Empleados!A:A,Empleados!B:B, Empleados no encontrado)} -> Maria Lopez | C4: =_xlfn.XLOOKUP(A4,Empleados!A:A,Empleados!C:C,"Cargo No encontrado") -> Tecnico | D4: =_xlfn.XLOOKUP(A4,Empleados!A:A,Empleados!E:E, "No encontrado") -> 55000 | E4: =D4*_xlfn.XLOOKUP("AFP",Deducciones!A:A,Deducciones!B:B,0) -> 1578.5 | F4: =D4*_xlfn.XLOOKUP("SFS",Deducciones!A:A,Deducciones!B:B,0) -> 1672 | G4: =D4*_xlfn.XLOOKUP("ISR",Deducciones!A:A,Deducciones!B:B,0) -> 5500 | H4: =D4-E4-F4-G4 -> 46249.5
A5: E003 | B5: {=_xlfn.XLOOKUP(A5,Empleados!A:A,Empleados!B:B, Empleados no encontrado)} -> Carlos Ruiz | C5: =_xlfn.XLOOKUP(A5,Empleados!A:A,Empleados!C:C,"Cargo No encontrado") -> Coordinador | D5: =_xlfn.XLOOKUP(A5,Empleados!A:A,Empleados!E:E, "No encontrado") -> 65000 | E5: =D5*_xlfn.XLOOKUP("AFP",Deducciones!A:A,Deducciones!B:B,0) -> 1865.5 | F5: =D5*_xlfn.XLOOKUP("SFS",Deducciones!A:A,Deducciones!B:B,0) -> 1976 | G5: =D5*_xlfn.XLOOKUP("ISR",Deducciones!A:A,Deducciones!B:B,0) -> 6500 | H5: =D5-E5-F5-G5 -> 54658.5
A6: E004 | B6: {=_xlfn.XLOOKUP(A6,Empleados!A:A,Empleados!B:B, Empleados no encontrado)} -> Ana Garcia | C6: =_xlfn.XLOOKUP(A6,Empleados!A:A,Empleados!C:C,"Cargo No encontrado") -> Analista | D6: =_xlfn.XLOOKUP(A6,Empleados!A:A,Empleados!E:E, "No encontrado") -> 50000 | E6: =D6*_xlfn.XLOOKUP("AFP",Deducciones!A:A,Deducciones!B:B,0) -> 1435 | F6: =D6*_xlfn.XLOOKUP("SFS",Deducciones!A:A,Deducciones!B:B,0) -> 1520 | G6: =D6*_xlfn.XLOOKUP("ISR",Deducciones!A:A,Deducciones!B:B,0) -> 5000 | H6: =D6-E6-F6-G6 -> 42045
A7: E005 | B7: {=_xlfn.XLOOKUP(A7,Empleados!A:A,Empleados!B:B, Empleados no encontrado)} -> Pedro Santos | C7: =_xlfn.XLOOKUP(A7,Empleados!A:A,Empleados!C:C,"Cargo No encontrado") -> Supervisor | D7: =_xlfn.XLOOKUP(A7,Empleados!A:A,Empleados!E:E, "No encontrado") -> 70000 | E7: =D7*_xlfn.XLOOKUP("AFP",Deducciones!A:A,Deducciones!B:B,0) -> 2009 | F7: =D7*_xlfn.XLOOKUP("SFS",Deducciones!A:A,Deducciones!B:B,0) -> 2128 | G7: =D7*_xlfn.XLOOKUP("ISR",Deducciones!A:A,Deducciones!B:B,0) -> 7000 | H7: =D7-E7-F7-G7 -> 58863
I13: =D5*_xlfn.XLOOKUP("SFS",Deducciones!A:A,Deducciones!B:B,0) -> 1976
I14: =D6*_xlfn.XLOOKUP("SFS",Deducciones!A:A,Deducciones!B:B,0) -> 1520
I15: =D7*_xlfn.XLOOKUP("SFS",Deducciones!A:A,Deducciones!B:B,0) -> 2128
I16: =D8*_xlfn.XLOOKUP("SFS",Deducciones!A:A,Deducciones!B:B,0) -> 0
